pystorm/__init__.py
pystorm/bolt.py
pystorm/component.py
pystorm/exceptions.py
pystorm/spout.py
pystorm/version.py
pystorm/serializers/__init__.py
pystorm/serializers/json_serializer.py
pystorm/serializers/msgpack_serializer.py
pystorm/serializers/serializer.py
pystorm-3.1.4.dist-info/METADATA
pystorm-3.1.4.dist-info/RECORD
pystorm-3.1.4.dist-info/WHEEL
pystorm-3.1.4.dist-info/pbr.json
pystorm-3.1.4.dist-info/top_level.txt
test/__init__.py
test/pystorm/__init__.py
test/pystorm/test_bolt.py
test/pystorm/test_component.py
test/pystorm/test_spout.py
test/pystorm/serializers/__init__.py
test/pystorm/serializers/serializer.py
test/pystorm/serializers/test_json_serializer.py
test/pystorm/serializers/test_msgpack_serializer.py
