Metadata-Version: 2.1
Name: pystorm
Version: 3.1.4
Summary: Battle-tested Apache Storm Multi-Lang implementation for Python.
Home-page: https://github.com/pystorm/pystorm
Author: Parsely, Inc.
Author-email: hello@parsely.com
License: Apache License 2.0
Platform: UNKNOWN
Provides-Extra: docs
Provides-Extra: all
Provides-Extra: lint
Provides-Extra: test
